my_nlp_package/__init__.py
my_nlp_package/sentiment.py
my_nlp_package-0.0.4.dist-info/METADATA
my_nlp_package-0.0.4.dist-info/WHEEL
my_nlp_package-0.0.4.dist-info/top_level.txt
my_nlp_package-0.0.4.dist-info/RECORD
